{
    "Changes": [
  {
"Action": "EditData",
"Target": "Data/Events/{{ModID}}_AncientGraveYard",
"Entries": {
  ////Intro////
"{{ModID}}_ShaavarIntroduction/t 1800 2400": "{{ModID}}_Tensions/-1000 -1000/farmer 37 55 1 FC.CorruptedGhost 37 41 0 FC.Shaavar 37 37 2/viewport 37 48 clamp true/skippable/animate FC.CorruptedGhost false true 460 8 9 8 9/showFrame FC.Shaavar 20/pause 1000/changeName FC.CorruptedGhost ???/speak FC.Shaavar \"{{i18n:ShaavarIntroduction.00}}\"/pause 250/speak FC.CorruptedGhost \"{{i18n:ShaavarIntroduction.01}}\"/playSound ghost/jump farmer 6/faceDirection farmer 0/pause 250/speed farmer 3/move farmer 0 -5 0 true/viewport move 0 -1 9000/pause 4000/speed FC.CorruptedGhost 4/speed farmer 5/move farmer 0 -6 0 true/move FC.CorruptedGhost 0 -3 0 true/globalFade/viewport -1000 -1000/playSound ghost/pause 300/screenFlash 1/playSound swordswipe/pause 250/playSound swordswipe/pause 250/playSound ghost/showFrame FC.Shaavar 0/warp FC.CorruptedGhost -3000 -3000/pause 1000/fade true/stopMusic/viewport 37 40/pause 200/speak FC.Shaavar \"{{i18n:ShaavarIntroduction.02}}\"/pause 250/move FC.Shaavar 0 4 2/pause 250/speak FC.Shaavar \"{{i18n:ShaavarIntroduction.03}}\"/playMusic SunRoom/pause 1000/emote FC.Shaavar 28/pause 250/textAbovehead FC.Shaavar \"{{i18n:ShaavarIntroduction.04}}\"/pause 200/move FC.Shaavar 0 1 2/pause 250/speak FC.Shaavar \"{{i18n:ShaavarIntroduction.05}}\"/pause 1000/emote FC.Shaavar 12/pause 1000/speak FC.Shaavar \"{{i18n:ShaavarIntroduction.06}}\"/pause 300/speak FC.Shaavar \"{{i18n:ShaavarIntroduction.07}}\"/pause 250/speak FC.Shaavar \"{{i18n:ShaavarIntroduction.08}}\"/pause 1000/quickQuestion {{i18n:ShaavarIntroduction.09}}(break)speak FC.Shaavar \"{{i18n:ShaavarIntroduction.10}}\"\\friendship FC.Shaavar 3(break)speak FC.Shaavar \"{{i18n:ShaavarIntroduction.11}}\"\\friendship FC.Shaavar -3/pause 300/emote FC.Shaavar 12/pause 300/speak FC.Shaavar \"{{i18n:ShaavarIntroduction.12}}\"/pause 250/move FC.Shaavar 0 -3 2/pause 200/speak FC.Shaavar \"{{i18n:ShaavarIntroduction.13}}\"/move FC.Shaavar 0 -3 0 true/pause 200/viewport move 0 -2 6000000/globalFade/viewport -1000 -1000/end",
}
},
]
}
